kappautils/__init__.py
kappautils/amp_utils.py
kappautils/context_managers.py
kappautils/memory_leak_utils.py
kappautils/model_utils.py
kappautils/param_checking.py
kappautils/images/__init__.py
kappautils/images/points_to_image.py
kappautils/images/png/__init__.py
kappautils/images/png/constants.py
kappautils/images/png/loaders.py
kappautils/images/png/writers.py
kappautils-0.0.7.dist-info/LICENSE
kappautils-0.0.7.dist-info/METADATA
kappautils-0.0.7.dist-info/WHEEL
kappautils-0.0.7.dist-info/top_level.txt
kappautils-0.0.7.dist-info/RECORD
